{
  "animateLoading": true,
  "borderRadius": "{{appsmith.theme.borderRadius.appBorderRadius}}",
  "bottomRow": 86,
  "boxShadow": "none",
  "buttonColor": "{{appsmith.theme.colors.primaryColor}}",
  "buttonStyle": "PRIMARY",
  "buttonVariant": "SECONDARY",
  "disabledWhenInvalid": false,
  "dynamicBindingPathList": [
    {
      "key": "buttonColor"
    },
    {
      "key": "borderRadius"
    }
  ],
  "dynamicTriggerPathList": [
    {
      "key": "onClick"
    }
  ],
  "isDefaultClickDisabled": true,
  "isDisabled": false,
  "isLoading": false,
  "isVisible": true,
  "key": "7no0ati6mx",
  "leftColumn": 0,
  "minWidth": 120,
  "mobileBottomRow": 22,
  "mobileLeftColumn": 31,
  "mobileRightColumn": 47,
  "mobileTopRow": 18,
  "needsErrorInfo": false,
  "onClick": "{{closeModal('')}}",
  "originalBottomRow": 79,
  "originalTopRow": 75,
  "parentId": "pfxlf4wdhi",
  "placement": "CENTER",
  "recaptchaType": "V3",
  "renderMode": "CANVAS",
  "resetFormOnClick": false,
  "responsiveBehavior": "hug",
  "rightColumn": 16,
  "text": "Odustani",
  "topRow": 82,
  "type": "BUTTON_WIDGET",
  "version": 1,
  "widgetId": "5owo750let",
  "widgetName": "Button2Copy"
}